[
  {
    "id": "sp1",
    "name": "Cặp học sinh phong cách ulzzang balo nam đi học thời trang ba lô du lịch thể thao giá rẻ",
    "price": 84500,
    "originalPrice": 130000,
    "image": "../img/product_img/student-bag/bag1.png",
    "sold": 98,
    "vote": 150,
    "discount": 0.35,
    "category": "home"
  },
  {
    "id": "sp2",
    "name": "Bộ mỹ thuật cho bé từ 5-6 tuổi",
    "price": 30000,
    "originalPrice": 50000,
    "image": "../img/product_img/art-supplies/my-thuat-tre-em.png",
    "sold": 553,
    "vote": 150,
    "discount": 0.4,
    "category": "home"
  },
  {
    "id": "sp3",
    "name": "Mein Kampf - Hitler's Autobiography (Vietnamese Version)",
    "price": 33000,
    "originalPrice": 60000,
    "image": "../img/product_img/art-supplies/hitler.png",
    "sold": 55,
    "vote": 150,
    "discount": 0.45,
    "category": "home"
  },
  {
    "id": "sp4",
    "name": "Lốc 12 chai keo dán giấy Thiên Long Điểm 10 TP-G08 - Hồ nước dán giấy",
    "price": 26000,
    "originalPrice": 40000,
    "image": "../img/product_img/glue-tape/keodannapvang.png",
    "sold": 51,
    "vote": 150,
    "discount": 0.35,
    "category": "home"
  },
  {
    "id": "sp5",
    "name": "Bộ 12 bút bi mực gel chất lượng cao dành cho học sinh, văn phòng, mực xanh/đen - kèm ruột bút thay thế.",
    "price": 27000,
    "originalPrice": 45000,
    "discount": 0.4,
    "image": "../img/product_img/pen/viet-xanh-005.png",
    "sold": 12,
    "vote": 345,
    "category": "home"
  },
  {
    "id": "sp6",
    "name": "Sổ tay mỹ thuật Minh Châu A4 100Gms Mc 578 màu vàng ngà",
    "price": 10500,
    "originalPrice": 15000,
    "discount": 0.3,
    "image": "../img/product_img/art-supplies/vo-my-thuat.png",
    "sold": 300,
    "vote": 342,
    "category": "home"
  },
  {
    "id": "sp7",
    "name": "Ba lô sành điệu, balô thời trang ,balô laptop hàn quốc SHINE TORE ST284",
    "price": 87000,
    "originalPrice": 290000,
    "discount": 0.7,
    "image": "../img/product_img/student-bag/cap-den.png",
    "sold": 50,
    "vote": 44,
    "category": "home"
  },
  {
    "id": "sp8",
    "name": "Liquid Glue 30ml",
    "price": 6300,
    "originalPrice": 9000,
    "discount": 0.3,
    "image": "../img/product_img/glue-tape/ho-dan-queen.png",
    "sold": 1400,
    "vote": 34,
    "category": "home"
  },
  {
    "id": "sp9",
    "name": "Ba lô da nam nữ thời trang , ba lô học sinh cấp 2,3 cao cấp SHINE TORE -342",
    "price": 113400,
    "originalPrice": 189000,
    "image": "../img/product_img/student-bag/bag2.png",
    "sold": 190,
    "vote": 150,
    "discount": 0.4,
    "category": "home"
  },
  {
    "id": "sp10",
    "name": "Bộ 5 - 10 - 20 bút bi Thiên Long TL-095 mực xanh đen, ngòi 0.5mm, kiểu dáng hiện đại, cầm thoải mái, trơn tru.",
    "price": 112000,
    "originalPrice": 160000,
    "image": "../img/product_img/pen/but_xanh_thienlong.png",
    "sold": 30,
    "vote": 150,
    "discount": 0.3,
    "category": "home"
  },
  {
    "id": "sp11",
    "name": "SỔ TAY SÁCH QUYỀN LỰC LÃNH ĐẠO HS36",
    "price": 54000,
    "originalPrice": 90000,
    "image": "../img/product_img/notebooks-docs/so-tay-lanh-dao.png",
    "sold": 36,
    "vote": 150,
    "discount": 0.4,
    "category": "home"
  },
  {
    "id": "sp12",
    "name": "Đắc Nhân Tâm - Bí Quyết Để Thành Công",
    "price": 31500,
    "originalPrice": 45000,
    "image": "../img/product_img/notebooks-docs/dac-nhan-tam.png",
    "sold": 360,
    "vote": 150,
    "discount": 0.3,
    "category": "home"
  }
]